mcp_nps_business_enrollment/__init__.py
mcp_nps_business_enrollment/api_client.py
mcp_nps_business_enrollment/models.py
mcp_nps_business_enrollment/server.py
mcp_nps_business_enrollment-0.1.2.dist-info/METADATA
mcp_nps_business_enrollment-0.1.2.dist-info/WHEEL
mcp_nps_business_enrollment-0.1.2.dist-info/entry_points.txt
mcp_nps_business_enrollment-0.1.2.dist-info/licenses/LICENSE
mcp_nps_business_enrollment-0.1.2.dist-info/RECORD
