Metadata-Version: 2.4
Name: mcp-nps-business-enrollment
Version: 0.1.2
Summary: MCP server for Korea National Pension Service business enrollment API
Project-URL: Homepage, https://github.com/Koomook/mcp_NPS_BusinessEnrollment
Project-URL: Repository, https://github.com/Koomook/mcp_NPS_BusinessEnrollment
Project-URL: Documentation, https://github.com/Koomook/mcp_NPS_BusinessEnrollment#readme
Project-URL: Bug Tracker, https://github.com/Koomook/mcp_NPS_BusinessEnrollment/issues
Author-email: Dave Goobong Jeong <bongbonggg97@gmail.com>
License: MIT
License-File: LICENSE
Keywords: api,business,enrollment,korea,mcp,nps,pension
Classifier: Development Status :: 3 - Alpha
Classifier: Intended Audience :: Developers
Classifier: License :: OSI Approved :: MIT License
Classifier: Programming Language :: Python :: 3
Classifier: Programming Language :: Python :: 3.10
Classifier: Programming Language :: Python :: 3.11
Classifier: Programming Language :: Python :: 3.12
Classifier: Programming Language :: Python :: 3.13
Requires-Python: >=3.10
Requires-Dist: httpx>=0.28.1
Requires-Dist: mcp[cli]>=1.13.0
Requires-Dist: pydantic>=2.11.7
Requires-Dist: python-dotenv>=1.1.1
